colorfield.py
django_html5_colorfield-2.0.dist-info/LICENSE
django_html5_colorfield-2.0.dist-info/METADATA
django_html5_colorfield-2.0.dist-info/WHEEL
django_html5_colorfield-2.0.dist-info/top_level.txt
django_html5_colorfield-2.0.dist-info/RECORD
