Metadata-Version: 2.1
Name: django-html5-colorfield
Version: 2.0
Summary: A HTML5 color field for Django models.
Home-page: https://github.com/knyghty/django-html5-colorfield
Author: Tom Carrick
Author-email: tom@carrick.eu
License: UNKNOWN
Keywords: django,color
Platform: UNKNOWN
Classifier: Development Status :: 5 - Production/Stable
Classifier: Environment :: Web Environment
Classifier: Framework :: Django
Classifier: License :: OSI Approved :: MIT License
Classifier: Operating System :: OS Independent
Classifier: Programming Language :: Python :: 3
